{"version": 0.6, "generator": "Overpass API 0.7.62.4 2390de5a", "osm3s": {"timestamp_osm_base": "2025-02-05T19:33:00Z", "copyright": "The data included in this document is from www.openstreetmap.org. The data is made available under ODbL."}, "elements": [{"type": "node", "id": 3818507323, "lat": -1.9470207, "lon": 32.9097663}, {"type": "node", "id": 4484391175, "lat": -2.0592946, "lon": 32.8455103}, {"type": "node", "id": 4484391176, "lat": -2.0591111, "lon": 32.8457262}, {"type": "node", "id": 4484391177, "lat": -2.0588876, "lon": 32.8459269}, {"type": "node", "id": 4484391178, "lat": -2.0589785, "lon": 32.8452169}, {"type": "node", "id": 4484391179, "lat": -2.0587574, "lon": 32.8454489}, {"type": "node", "id": 4484391180, "lat": -2.0588128, "lon": 32.8458982}, {"type": "node", "id": 4484391181, "lat": -2.0586994, "lon": 32.8462224}, {"type": "node", "id": 4484391182, "lat": -2.0587488, "lon": 32.8464158}, {"type": "node", "id": 4484391183, "lat": -2.0586908, "lon": 32.8466135}, {"type": "node", "id": 4484391184, "lat": -2.0588175, "lon": 32.8470346}, {"type": "node", "id": 4484391185, "lat": -2.0589356, "lon": 32.8472731}, {"type": "node", "id": 4484391186, "lat": -2.0589914, "lon": 32.8475481}, {"type": "node", "id": 4484391187, "lat": -2.0590515, "lon": 32.8475653}, {"type": "node", "id": 4484391188, "lat": -2.0590558, "lon": 32.8476513}, {"type": "node", "id": 4484391189, "lat": -2.0587208, "lon": 32.8480445}, {"type": "node", "id": 4484391190, "lat": -2.0586049, "lon": 32.8481003}, {"type": "node", "id": 4484391191, "lat": -2.0583708, "lon": 32.8482937}, {"type": "node", "id": 4484391192, "lat": -2.0582055, "lon": 32.8484463}, {"type": "node", "id": 4484391194, "lat": -2.0589937, "lon": 32.8477242}, {"type": "node", "id": 4518944149, "lat": -1.9400577, "lon": 32.867346}, {"type": "node", "id": 4518944152, "lat": -1.9411233, "lon": 32.8477849}, {"type": "node", "id": 4518944153, "lat": -1.9411229, "lon": 32.8772987}, {"type": "node", "id": 4518944154, "lat": -1.9411797, "lon": 32.848308}, {"type": "node", "id": 4518944155, "lat": -1.9412116, "lon": 32.8788246}, {"type": "node", "id": 4518944156, "lat": -1.9412864, "lon": 32.8801937}, {"type": "node", "id": 4518944157, "lat": -1.9413891, "lon": 32.8622049}, {"type": "node", "id": 4518944158, "lat": -1.94126, "lon": 32.8429811}, {"type": "node", "id": 4518944159, "lat": -1.9414058, "lon": 32.8824869}, {"type": "node", "id": 4518944160, "lat": -1.9414409, "lon": 32.8509504}, {"type": "node", "id": 4518944161, "lat": -1.9417072, "lon": 32.8850303}, {"type": "node", "id": 4518944162, "lat": -1.9414529, "lon": 32.8761423}, {"type": "node", "id": 4518944163, "lat": -1.941764, "lon": 32.8449338}, {"type": "node", "id": 4518944165, "lat": -1.9424369, "lon": 32.8875084}, {"type": "node", "id": 4518944166, "lat": -1.9427313, "lon": 32.8885982}, {"type": "node", "id": 4518944168, "lat": -1.9440547, "lon": 32.8929075}, {"type": "node", "id": 4518944169, "lat": -1.9441325, "lon": 32.8948507}, {"type": "node", "id": 4518944170, "lat": -1.9456343, "lon": 32.9026635}, {"type": "node", "id": 4518944174, "lat": -1.9464653, "lon": 32.9045202}, {"type": "node", "id": 4518944178, "lat": -1.9472833, "lon": 32.9086909}, {"type": "node", "id": 4518944179, "lat": -1.9475207, "lon": 32.9067624}, {"type": "node", "id": 4518964669, "lat": -1.927655, "lon": 32.8282351}, {"type": "node", "id": 4518964670, "lat": -1.9280021, "lon": 32.8285628}, {"type": "node", "id": 4518964671, "lat": -1.9284203, "lon": 32.8294855}, {"type": "node", "id": 4518964672, "lat": -1.9285544, "lon": 32.8305396}, {"type": "node", "id": 4518964676, "lat": -1.9294905, "lon": 32.8314023}, {"type": "node", "id": 4518964682, "lat": -1.9319539, "lon": 32.833522}, {"type": "node", "id": 4518964687, "lat": -1.9334073, "lon": 32.8346805}, {"type": "node", "id": 4518973690, "lat": -1.934184, "lon": 32.836481}, {"type": "node", "id": 4518973691, "lat": -1.934531, "lon": 32.839765}, {"type": "node", "id": 4518973701, "lat": -1.9369332, "lon": 32.8407737}, {"type": "node", "id": 4518973704, "lat": -1.9384455, "lon": 32.8474196}, {"type": "node", "id": 4518973707, "lat": -1.9402178, "lon": 32.8477905}, {"type": "node", "id": 4518973708, "lat": -1.9402631, "lon": 32.848229}, {"type": "node", "id": 4518973723, "lat": -1.9436509, "lon": 32.8915911, "tags": {"ford": "yes"}}, {"type": "node", "id": 4518973731, "lat": -1.9451078, "lon": 32.9004541}, {"type": "node", "id": 4518980036, "lat": -1.9470457, "lon": 32.9053584}, {"type": "node", "id": 4518980037, "lat": -1.9473808, "lon": 32.9059485}, {"type": "node", "id": 4518980038, "lat": -1.9473808, "lon": 32.9081801}, {"type": "node", "id": 6520658837, "lat": -1.9434268, "lon": 32.8907436}, {"type": "node", "id": 8630213348, "lat": -1.9474773, "lon": 32.9063541}, {"type": "node", "id": 8630213349, "lat": -1.9476167, "lon": 32.9071426}, {"type": "node", "id": 8630213350, "lat": -1.947614, "lon": 32.9075181}, {"type": "node", "id": 8630228872, "lat": -1.9414833, "lon": 32.8838289}, {"type": "node", "id": 8630228873, "lat": -1.941164, "lon": 32.8769751}, {"type": "node", "id": 8630228874, "lat": -1.9415155, "lon": 32.8747201}, {"type": "node", "id": 8630228876, "lat": -1.9430759, "lon": 32.889692}, {"type": "node", "id": 8630240848, "lat": -1.9413935, "lon": 32.8620489}, {"type": "node", "id": 8630240849, "lat": -1.941419, "lon": 32.8611535}, {"type": "node", "id": 8630240850, "lat": -1.9414833, "lon": 32.8568673}, {"type": "node", "id": 8630240851, "lat": -1.9411563, "lon": 32.8729391}, {"type": "node", "id": 8630240852, "lat": -1.9410544, "lon": 32.8719681}, {"type": "node", "id": 8630270189, "lat": -1.9415798, "lon": 32.851578}, {"type": "node", "id": 8630270190, "lat": -1.9415744, "lon": 32.8526884}, {"type": "node", "id": 8630270191, "lat": -1.9415691, "lon": 32.8537613}, {"type": "node", "id": 8630270192, "lat": -1.9413278, "lon": 32.8498185}, {"type": "node", "id": 8630270193, "lat": -1.9345082, "lon": 32.8393525}, {"type": "node", "id": 8630270194, "lat": -1.9343849, "lon": 32.838875}, {"type": "node", "id": 8630270195, "lat": -1.9343205, "lon": 32.8379792}, {"type": "node", "id": 8630270196, "lat": -1.9356448, "lon": 32.8409028}, {"type": "node", "id": 8630270197, "lat": -1.9355268, "lon": 32.8405863}, {"type": "node", "id": 8630270198, "lat": -1.9357788, "lon": 32.8410852}, {"type": "node", "id": 8630270199, "lat": -1.9415101, "lon": 32.846337}, {"type": "node", "id": 8632619544, "lat": -1.8561233, "lon": 32.8466263}, {"type": "node", "id": 8632619591, "lat": -1.8529594, "lon": 32.8398299}, {"type": "node", "id": 8632619592, "lat": -1.853013, "lon": 32.8402698}, {"type": "node", "id": 8632619593, "lat": -1.8529326, "lon": 32.8404575}, {"type": "node", "id": 8632619594, "lat": -1.8529809, "lon": 32.841863}, {"type": "node", "id": 8632619595, "lat": -1.8532972, "lon": 32.8425282}, {"type": "node", "id": 8632619596, "lat": -1.8534474, "lon": 32.8433114}, {"type": "node", "id": 8632619597, "lat": -1.8536779, "lon": 32.843821}, {"type": "node", "id": 8632619598, "lat": -1.8537262, "lon": 32.8439766}, {"type": "node", "id": 8632619599, "lat": -1.8539085, "lon": 32.844792}, {"type": "node", "id": 8632619600, "lat": -1.8541015, "lon": 32.845264}, {"type": "node", "id": 8632619601, "lat": -1.8543428, "lon": 32.8454464}, {"type": "node", "id": 8632619602, "lat": -1.8547396, "lon": 32.8456664}, {"type": "node", "id": 8632619603, "lat": -1.8548576, "lon": 32.8457737}, {"type": "node", "id": 8632619604, "lat": -1.855367, "lon": 32.8461384}, {"type": "node", "id": 8632619605, "lat": -1.8558067, "lon": 32.846353}, {"type": "node", "id": 8632619606, "lat": -1.8560533, "lon": 32.8466105}, {"type": "node", "id": 8633725139, "lat": -1.9412312, "lon": 32.8791833}, {"type": "node", "id": 8633725286, "lat": -1.9411274, "lon": 32.8773755}, {"type": "node", "id": 8633725326, "lat": -1.9413318, "lon": 32.8764743}, {"type": "node", "id": 8633725376, "lat": -1.9412461, "lon": 32.8794569}, {"type": "node", "id": 8633725383, "lat": -1.9416213, "lon": 32.8845692}, {"type": "node", "id": 8636131805, "lat": -1.9472545, "lon": 32.9057261}, {"type": "node", "id": 8636131817, "lat": -1.9457277, "lon": 32.9028721}, {"type": "node", "id": 8636131820, "lat": -1.9463921, "lon": 32.9043566}, {"type": "node", "id": 8636131834, "lat": -1.9473187, "lon": 32.9058391}, {"type": "node", "id": 8636131844, "lat": -1.9476148, "lon": 32.9074055}, {"type": "node", "id": 8637871440, "lat": -1.9470995, "lon": 32.9094712}, {"type": "node", "id": 8641637698, "lat": -1.9413749, "lon": 32.8818933}, {"type": "node", "id": 8641685447, "lat": -1.9451407, "lon": 32.9005921}, {"type": "node", "id": 8641690120, "lat": -1.9428963, "lon": 32.8891071}, {"type": "node", "id": 8641690133, "lat": -1.9429638, "lon": 32.8893271}, {"type": "node", "id": 10840003944, "lat": -1.941494, "lon": 32.875793}, {"type": "way", "id": 451614021, "nodes": [4484391175, 4484391176, 4484391177], "tags": {"highway": "unclassified", "surface": "unpaved"}}, {"type": "way", "id": 451614022, "nodes": [4484391178, 4484391179, 4484391180, 4484391181, 4484391182, 4484391183, 4484391184, 4484391185, 4484391186, 4484391187, 4484391188, 4484391194, 4484391189, 4484391190, 4484391191, 4484391192], "tags": {"highway": "unclassified", "surface": "unpaved"}}, {"type": "way", "id": 455498809, "nodes": [3818507323, 8637871440, 4518944178, 4518980038, 8630213350, 8636131844, 8630213349, 4518944179, 8630213348, 4518980037, 8636131834, 8636131805, 4518980036, 4518944174, 8636131820, 8636131817, 4518944170, 8641685447, 4518973731, 4518944169, 4518944168, 4518973723, 6520658837, 8630228876, 8641690133, 8641690120, 4518944166, 4518944165, 4518944161, 8633725383, 8630228872, 4518944159, 8641637698, 4518944156, 8633725376, 8633725139, 4518944155, 8633725286, 4518944153, 8630228873, 8633725326, 4518944162, 10840003944, 8630228874, 8630240851, 8630240852, 4518944149, 4518944157, 8630240848, 8630240849, 8630240850, 8630270191, 8630270190, 8630270189, 4518944160, 8630270192, 4518944154, 4518944152, 8630270199, 4518944163, 4518944158], "tags": {"highway": "unclassified"}}, {"type": "way", "id": 455500087, "nodes": [4518973708, 4518973707, 4518973704, 4518973701, 8630270198, 8630270196, 8630270197, 4518973691, 8630270193, 8630270194, 8630270195, 4518973690, 4518964687, 4518964682, 4518964676, 4518964672, 4518964671, 4518964670, 4518964669], "tags": {"highway": "unclassified"}}, {"type": "way", "id": 931073855, "nodes": [8632619591, 8632619592, 8632619593, 8632619594, 8632619595, 8632619596, 8632619597, 8632619598, 8632619599, 8632619600, 8632619601, 8632619602, 8632619603, 8632619604, 8632619605, 8632619606, 8632619544], "tags": {"highway": "residential", "source": "maxar"}}]}